naverdict/__init__.py
naverdict/cli.py
naverdict/constants.py
naverdict/exceptions.py
naverdict/search.py
naverdict-1.0.0.dist-info/LICENSE.md
naverdict-1.0.0.dist-info/METADATA
naverdict-1.0.0.dist-info/WHEEL
naverdict-1.0.0.dist-info/entry_points.txt
naverdict-1.0.0.dist-info/top_level.txt
naverdict-1.0.0.dist-info/RECORD
