Metadata-Version: 2.1
Name: naverdict
Version: 1.0.0
Summary: Access Naver dictionary using Python
Author-email: Reinier Koops <reinier.koops@outlook.com>
License: The MIT License (MIT)
Project-URL: Documentation, https://reinierkoops.github.io/naverdict/
Project-URL: Repository, https://github.com/ReinierKoops/naverdict.git
Project-URL: Changelog, https://github.com/ReinierKoops/naverdict/releases
Classifier: License :: OSI Approved :: MIT License
Classifier: Operating System :: OS Independent
Classifier: Programming Language :: Python
Classifier: Programming Language :: Python :: 3
Classifier: Programming Language :: Python :: 3.10
Classifier: Programming Language :: Python :: 3.11
Classifier: Programming Language :: Python :: 3.12
Classifier: Programming Language :: Python :: 3 :: Only
Requires-Python: >=3.10
License-File: LICENSE.md
Requires-Dist: beautifulsoup4>=4.0.0
Requires-Dist: selenium>=4.0.0
Requires-Dist: webdriver_manager>=4.0.0
Requires-Dist: requests>=2.0.0
Requires-Dist: click>=8.0.0
Provides-Extra: dev
Requires-Dist: black>=24.0.0; extra == "dev"
Requires-Dist: pytest>=8.0.0; extra == "dev"
Requires-Dist: isort>=5.0.0; extra == "dev"
Requires-Dist: pre-commit>=4.0.0; extra == "dev"
Requires-Dist: ruff>=0.8.0; extra == "dev"
Requires-Dist: mkdocs>=1.6.0; extra == "dev"
Requires-Dist: mkdocs-material>=9.0.0; extra == "dev"
